ipython_venv_path_prompt/__init__.py
ipython_venv_path_prompt/ipython_venv_path_prompt.py
ipython_venv_path_prompt-0.1.4.dist-info/LICENSE
ipython_venv_path_prompt-0.1.4.dist-info/METADATA
ipython_venv_path_prompt-0.1.4.dist-info/WHEEL
ipython_venv_path_prompt-0.1.4.dist-info/top_level.txt
ipython_venv_path_prompt-0.1.4.dist-info/RECORD
