Metadata-Version: 2.1
Name: ipython-venv-path-prompt
Version: 0.1.4
Summary: A simple IPython extension to show the path and virtualenv in the prompt.
Home-page: https://github.com/javidcf/ipython_venv_path_prompt
Author: Javier Dehesa
Author-email: javidcf@gmail.com
License: MIT
Keywords: ipython venv virtualenv path cwd prompt
Platform: UNKNOWN
Classifier: Development Status :: 4 - Beta
Classifier: Environment :: Console
Classifier: Intended Audience :: Developers
Classifier: Framework :: IPython
Classifier: License :: OSI Approved :: MIT License
Classifier: Programming Language :: Python
Classifier: Topic :: Utilities
Requires-Dist: ipython
